tess_backml/__init__.py
tess_backml/bkg_data.py
tess_backml/corrector.py
tess_backml/data/dark_frame_indices_tess_ffi.pkl
tess_backml/data/straps.csv
tess_backml/utils.py
tess_backml-0.3.3.dist-info/METADATA
tess_backml-0.3.3.dist-info/WHEEL
tess_backml-0.3.3.dist-info/RECORD
