Metadata-Version: 2.3
Name: tess-backml
Version: 0.3.3
Summary: 
Author: Jorge Martinez-Palomera
Author-email: jorgemarpa@ug.uchile.cl
Requires-Python: >=3.9,<3.13
Classifier: Programming Language :: Python :: 3
Classifier: Programming Language :: Python :: 3.9
Classifier: Programming Language :: Python :: 3.10
Classifier: Programming Language :: Python :: 3.11
Classifier: Programming Language :: Python :: 3.12
Requires-Dist: astropy (>=5.3.4,<7.0)
Requires-Dist: matplotlib (>=3.9.0,<4.0.0)
Requires-Dist: numpy (>1.26,<3.0)
Requires-Dist: pandas (>=2.2.3,<3.0.0)
Requires-Dist: scipy (>=1.13.0,<2.0.0)
Requires-Dist: tesscube (>=1.2.1,<2.0.0)
Requires-Dist: tqdm (>=4.67.1,<5.0.0)
